{
    "type": "Reading",
    "name": "Distributed systems for fun and profit",
    "origin": {
        "name": "Notes",
        "link": ""
    },
    "companies": [
        "",
        ""
    ],
    "categories": [
        {
            "name": "Books",
            "children": []
        },
        {
            "name": "Authors",
            "children": [
                {
                    "name": "Mikito Takada",
                    "children": [
                        {
                            "name": "alias",
                            "children":[
                                {
                                    "name": "mixu",
                                    "children": []
                                }
                            ]
                        }
                    ]
                }
            ]
        }
    ],
    "tags": [
        "Distributed Systems",
        "Cloud Computing"
    ],
    "buckets": [
        "",
        ""
    ]
}