{
    "type": "Coding",
    "name": "Four Sum",
    "origin": {
        "name": "InterviewBit",
        "link": "https://www.interviewbit.com/problems/4-sum/"
    },
    "companies": [
        "Amazon",
        "Google"
    ],
    "categories": [
        {
            "name": "Courses",
            "children": [
                {
                    "name": "Programming",
                    "children": []
                }
            ]
        }
    ],
    "tags": [
        "Hashing"
    ],
    "buckets": [
        "Hash Search"
    ]
}