{
    "type": "Coding",
    "name": "No-repeat Substring",
    "origin": {
        "name": "Educative",
        "link": "https://www.educative.io/collection/page/5668639101419520/5671464854355968/5485010335301632"
    },
    "companies": [
        "",
        ""
    ],
    "categories": [
        {
            "name": "Courses",
            "children": [
                {
                    "name": "Grokking the Coding Interview: Patterns for Coding Questions",
                    "children": []
                }
            ]
        },
        {
            "name": "Difficulty",
            "children": [
                {
                    "name": "Hard",
                    "children": []
                }
            ]
        },
        {
            "name": "Pattern",
            "children": [
                {
                    "name": "Sliding Window",
                    "children": []
                }
            ]
        }
    ],
    "tags": [
        "Arrays"
    ],
    "buckets": [
        "",
        ""
    ]
}