{
    "type": "Coding",
    "name": "283. Move Zeroes",
    "origin": {
        "name": "LeetCode",
        "link": "https://leetcode.com/problems/move-zeroes/description/"
    },
    "companies": [
        "Facebook",
        "Google",
        "SAP",
        "Walmart Labs",
        "Bloomberg",
        "Microsoft",
        "Apple",
        "eBay",
        "Uber",
        "Paypal",
        "Baidu",
        "Lyft",
        "Amazon",
        "Yahoo",
        "Oracle"
    ],
    "categories": [
        {
            "name": "Problems",
            "children": [
                {
                    "name": "Algorithms",
                    "children": []
                }
            ]
        },
        {
            "name": "Difficulty",
            "children": [
                {
                    "name": "Easy",
                    "children": []
                }
            ]
        }
    ],
    "tags": [
        "Array",
        "Two Pointers"
    ],
    "buckets": [
        "",
        ""
    ]
}