{
    "type": "Coding",
    "name": "Sum Of Pairwise Hamming Distance",
    "origin": {
        "name": "InterviewBit",
        "link": "https://www.interviewbit.com/problems/sum-of-pairwise-hamming-distance/"
    },
    "companies": [
        "Google"
    ],
    "categories": [
        {
            "name": "Courses",
            "children": [
                {
                    "name": "Programming",
                    "children": []
                }
            ]
        }
    ],
    "tags": [
        "Math"
    ],
    "buckets": [
        "AdHoc"
    ]
}