{
    "type": "Coding",
    "name": "Grid Unique Paths",
    "origin": {
        "name": "InterviewBit",
        "link": "https://www.interviewbit.com/problems/grid-unique-paths/"
    },
    "companies": [
        "Google",
        "Amazon",
        "Microsoft",
        "Adobe"
    ],
    "categories": [
        {
            "name": "Courses",
            "children": [
                {
                    "name": "Programming",
                    "children": []
                }
            ]
        }
    ],
    "tags": [
        "Math"
    ],
    "buckets": [
        "Combinatorics"
    ]
}